ASUkit/CGCNN_atom_emb.json
ASUkit/MatgenKit.py
ASUkit/__init__.py
ASUkit/cry2graph.py
ASUkit/_utility/WPEMsim.py
ASUkit/_utility/__init__.py
ASUkit/_utility/_funs.py
ASUkit-1.0.0.dist-info/METADATA
ASUkit-1.0.0.dist-info/WHEEL
ASUkit-1.0.0.dist-info/top_level.txt
ASUkit-1.0.0.dist-info/RECORD
