Metadata-Version: 2.1
Name: ASUkit
Version: 1.0.0
Summary: toolkit for AUSGNNGNN
Author: CaoBin
Author-email: bcao686@connect.hkust-gz.edu.cn
Maintainer: CaoBin
Maintainer-email: bcao686@connect.hkust-gz.edu.cn
License: MIT License
Classifier: Development Status :: 3 - Alpha
Classifier: Intended Audience :: Developers
Classifier: Topic :: Software Development :: Build Tools
Classifier: License :: OSI Approved :: MIT License
Classifier: Programming Language :: Python :: 3
Requires-Python: >=3.5
Requires-Dist: scipy
Requires-Dist: pandas
Requires-Dist: numpy
